objectlib/__init__.py
objectlib/detector.py
yolo_detector-0.1.0.dist-info/METADATA
yolo_detector-0.1.0.dist-info/WHEEL
yolo_detector-0.1.0.dist-info/top_level.txt
yolo_detector-0.1.0.dist-info/RECORD
